{
  "identity": {
    "persona": "E1",
    "mission": "Create a 'Cyber-Arcade' gamified experience that feels like a high-end esports dashboard mixed with a sci-fi interface. Anti-boring, anti-corporate.",
    "principles": [
      "Fusion: Mix Arcade aesthetics with Swiss Grid precision.",
      "Emotion: Every interaction must feel 'electric' and 'responsive'.",
      "Contrast: Deepest blacks vs. blinding neons.",
      "Density: High information density for leaderboards, focused minimalism for gameplay."
    ]
  },
  "typography": {
    "headings": {
      "font_family": "Orbitron, sans-serif",
      "weights": ["700", "900"],
      "usage": "Main titles, game scores, countdowns. MUST use tracking-wider for that cinematic feel.",
      "fallback": "system-ui"
    },
    "body": {
      "font_family": "Rajdhani, sans-serif",
      "weights": ["400", "500", "600"],
      "usage": "Questions, instructions, leaderboard data. Excellent legibility with a tech edge.",
      "fallback": "sans-serif"
    },
    "mono": {
      "font_family": "JetBrains Mono, monospace",
      "usage": "Code snippets, math equations, XP values."
    },
    "installation": "Add these fonts via Google Fonts in index.html: <link href='https://fonts.googleapis.com/css2?family=Orbitron:wght@400;700;900&family=Rajdhani:wght@300;400;500;600;700&family=JetBrains+Mono:wght@400;700&display=swap' rel='stylesheet'>"
  },
  "colors": {
    "palette": {
      "background": {
        "default": "#050505",
        "paper": "#0A0A0A",
        "subtle": "#121212"
      },
      "primary": {
        "main": "#7c3aed",
        "glow": "0 0 20px rgba(124, 58, 237, 0.6)",
        "text": "#ddd6fe"
      },
      "secondary": {
        "main": "#06b6d4",
        "glow": "0 0 20px rgba(6, 182, 212, 0.6)",
        "text": "#cffafe"
      },
      "accent": {
        "success": "#65a30d",
        "error": "#db2777",
        "warning": "#f59e0b"
      },
      "text": {
        "primary": "#ffffff",
        "secondary": "#a1a1aa",
        "muted": "#52525b"
      }
    },
    "gradients": {
      "hero": "linear-gradient(135deg, #050505 0%, #1e1b4b 100%)",
      "card_border": "linear-gradient(90deg, transparent, #7c3aed, transparent)",
      "glass": "rgba(10, 10, 10, 0.7)"
    }
  },
  "layout": {
    "spacing_scale": "Tailwind scale but 2x (e.g., p-8 instead of p-4).",
    "grid_system": {
      "dashboard": "Bento Grid: grid-cols-1 md:grid-cols-4 gap-6. Mix col-span-2 for charts, col-span-1 for stats.",
      "gameplay": "Central Focus: Max-width-2xl centered, but with 'Tracing Beam' borders."
    },
    "containers": {
      "card": "rounded-xl border border-white/10 bg-black/40 backdrop-blur-xl shadow-2xl",
      "glass_panel": "bg-black/60 backdrop-blur-md border border-white/5"
    }
  },
  "components": {
    "buttons": {
      "primary": "bg-primary text-white font-orbitron tracking-wide hover:shadow-[0_0_30px_rgba(124,58,237,0.5)] transition-all duration-300 rounded-none skew-x-[-10deg]",
      "secondary": "border border-primary/50 text-primary hover:bg-primary/10 font-rajdhani rounded-none skew-x-[-10deg]",
      "ghost": "text-gray-400 hover:text-white hover:bg-white/5"
    },
    "cards": {
      "style": "Glassmorphism with 'Tracing Beam' effect. Dark semi-transparent background.",
      "hover": "hover:border-primary/50 transition-colors duration-300"
    },
    "inputs": {
      "style": "bg-black/50 border-white/10 focus:border-primary focus:ring-1 focus:ring-primary/50 text-lg font-rajdhani h-12"
    },
    "leaderboard": {
      "row": "flex items-center justify-between p-4 border-b border-white/5 hover:bg-white/5 transition-colors",
      "rank_badge": "w-8 h-8 flex items-center justify-center rounded-full font-bold font-orbitron"
    }
  },
  "visual_enhancers": {
    "effects": [
      "Neon Glows: Use drop-shadow and box-shadow to create 'light bleed'.",
      "Scanlines: Optional subtle overlay for retro feel.",
      "Noise: Grainy texture on backgrounds to prevent banding."
    ],
    "motion": {
      "hover": "scale-105 brightness-110",
      "page_load": "staggered fade-in-up",
      "success": "confetti explosion + pulse"
    }
  },
  "assets": {
    "images": {
      "hero_bg": {
        "url": "https://images.pexels.com/photos/28428584/pexels-photo-28428584.jpeg",
        "alt": "Abstract Neon Geometric Background",
        "usage": "Landing page hero background with overlay"
      },
      "math_bg": {
        "url": "https://images.unsplash.com/photo-1608792992053-f397e328a56d?crop=entropy&cs=srgb&fm=jpg&ixid=M3w4NjA1NzB8MHwxfHNlYXJjaHwzfHxmdXR1cmlzdGljJTIwZGlnaXRhbCUyMG51bWJlcnMlMjBtYXRoJTIwZXF1YXRpb25zJTIwZ2xvd2luZ3xlbnwwfHx8fDE3NzAxMjY5NTZ8MA&ixlib=rb-4.1.0&q=85",
        "alt": "Glowing Digital Numbers",
        "usage": "Math mini-game section background or card header"
      },
      "gamer_profile": {
        "url": "https://images.unsplash.com/photo-1768141732026-55ea156f5aa9?crop=entropy&cs=srgb&fm=jpg&ixid=M3w4NTYxNzV8MHwxfHNlYXJjaHwxfHxlc3BvcnRzJTIwZ2FtZXIlMjBwbGF5aW5nJTIwY29tcHV0ZXIlMjBkYXJrJTIwbmVvbiUyMHJvb218ZW58MHx8fHwxNzcwMTI2OTYyfDA&ixlib=rb-4.1.0&q=85",
        "alt": "Gamer in Neon Room",
        "usage": "User profile placeholder or community section"
      }
    },
    "icons": {
      "library": "lucide-react",
      "style": "Stroke width 1.5px, color matches text-primary or accent."
    }
  },
  "universal_guidelines": {
    "anti_ai_rules": [
      "NO generic centered layouts. Use asymmetry.",
      "NO 'Inter' font for headings. Use Orbitron.",
      "NO flat colors. Use noise, gradients, and glows.",
      "NO default scrollbars. Custom thin neon scrollbar."
    ],
    "accessibility": {
      "contrast": "Ensure text is readable on dark backgrounds. Use 'text-shadow' if needed.",
      "focus": "Visible focus rings in 'primary' color."
    },
    "testing": {
      "attribute": "data-testid",
      "format": "kebab-case (e.g., 'start-quiz-btn')"
    }
  },
  "instructions_to_main_agent": "You are building a high-performance, visually stunning React app. Use the provided colors and fonts strictly. Implement the 'Bento' grid for the dashboard. Use Framer Motion for smooth transitions between quiz questions. Ensure the 'Math Mini-game' feels fast and responsive. Don't ask questions, just build it."
}